{
  "DryRun": false,
  "Resources": [
    "i-0969b054fcede4a59"
  ],
  "Tags": [
    {
      "Key": "BackupPlan",
      "Value": "Monthly"
    },
    {
      "Key": "Version",
      "Value": "1.0"
    },
    {
      "Key": "DataClassification",
      "Value": "None"
    },
    {
      "Key": "Usage",
      "Value": "Project"
    },
    {
      "Key": "Type",
      "Value": "adhoc"
    },
    {
      "Key": "CreatedOn",
      "Value": "NoInfo"
    },
    {
      "Key": "ApplicationName",
      "Value": "Hermes"
    },
    {
      "Key": "Department",
      "Value": "HMS"
    },
    {
      "Key": "TechStack",
      "Value": "PsCharm"
    },
    {
      "Key": "LastUpdated",
      "Value": "NoInfo"
    },
    {
      "Key": "Automated",
      "Value": "False"
    },
    {
      "Key": "CostCenter",
      "Value": "Operations"
    },
    {
      "Key": "Project",
      "Value": "CCMS"
    },
    {
      "Key": "Name",
      "Value": "EC2-RHEL-PSCHM-Stage2"
    },
    {
      "Key": "CreatedBy",
      "Value": "dselvaraj"
    },
    {
      "Key": "Infrastructure",
      "Value": "False"
    },
    {
      "Key": "WeekendShutdown",
      "Value": "True"
    }
  ]
}
